pytest_result_notify-0.1.1.dist-info/METADATA
pytest_result_notify-0.1.1.dist-info/WHEEL
pytest_result_notify-0.1.1.dist-info/entry_points.txt
pytest_result_notify/__init__.py
pytest_result_notify/components/__init__.py
pytest_result_notify/components/slack_client.py
pytest_result_notify/components/utils.py
pytest_result_notify/plugin.py
pytest_result_notify-0.1.1.dist-info/RECORD
