Metadata-Version: 2.1
Name: pytest-result-notify
Version: 0.1.1
Summary: Default template for PDM package
Author-Email: "yanlong.wu" <yanlong.wu@smartx.com>
License: MIT
Requires-Python: >=3.8
Requires-Dist: pytest>=8.3.5
Requires-Dist: requests>=2.32.3
